LICENSE
README.md
setup.py
sibase/__init__.py
sibase/units.py
sibase.egg-info/PKG-INFO
sibase.egg-info/SOURCES.txt
sibase.egg-info/dependency_links.txt
sibase.egg-info/top_level.txt