Metadata-Version: 2.1
Name: sibase
Version: 0.2.0
Summary: A basic python package that converts numerical strings with units to base units
Home-page: https://github.com/zceemja/si-base
Author: Mindaugas Jarmolovičius
Author-email: zceemja@ucl.ac.uk
License: UNKNOWN
Platform: UNKNOWN
Classifier: Intended Audience :: Science/Research
Classifier: Programming Language :: Python :: 3
Classifier: License :: OSI Approved :: MIT License
Classifier: Operating System :: OS Independent
Requires-Python: >=3.6
License-File: LICENSE
